Metadata-Version: 2.1
Name: knowhere
Version: 1.0.0
Summary: An in memory cache with efficient expiration
Home-page: https://github.com/sankalpjonn/knowhere
Author: Sankalp Jonna
Author-email: sankalpjonna@gmail.com
License: MIT
Keywords: cache,memory,in memory,expiration,ttl
Platform: UNKNOWN
